lsdyna_mesh_reader/__init__.py
lsdyna_mesh_reader/_deck.cp311-win_amd64.pyd
lsdyna_mesh_reader/_deck.pyi
lsdyna_mesh_reader/deck.py
lsdyna_mesh_reader/examples/__init__.py
lsdyna_mesh_reader/examples/bird.k
lsdyna_mesh_reader/examples/birdball.k
lsdyna_mesh_reader/examples/bracket.k
lsdyna_mesh_reader/examples/ex_13_thick_shell_elform_2.k
lsdyna_mesh_reader/examples/EXP_SC_JOINT_SCREW.key
lsdyna_mesh_reader/examples/wheel.k
lsdyna_mesh_reader/py.typed
lsdyna_mesh_reader-0.1.4.dist-info/METADATA
lsdyna_mesh_reader-0.1.4.dist-info/WHEEL
lsdyna_mesh_reader-0.1.4.dist-info/licenses/LICENSE
lsdyna_mesh_reader-0.1.4.dist-info/RECORD
