Metadata-Version: 2.1
Name: lsdyna-mesh-reader
Version: 0.1.4
Summary: Read nodes and elements from LS-DYNA decks.
Author-Email: Alex Kaszynski <akascap@gmail.com>
Classifier: Development Status :: 4 - Beta
Classifier: Intended Audience :: Science/Research
Classifier: Topic :: Scientific/Engineering :: Information Analysis
Classifier: License :: OSI Approved :: MIT License
Classifier: Operating System :: Microsoft :: Windows
Classifier: Operating System :: POSIX
Classifier: Operating System :: MacOS
Classifier: Programming Language :: Python :: 3.9
Classifier: Programming Language :: Python :: 3.10
Classifier: Programming Language :: Python :: 3.11
Classifier: Programming Language :: Python :: 3.12
Classifier: Programming Language :: Python :: 3.13
Project-URL: Documentation, https://akaszynski.github.io/lsdyna-mesh-reader/
Project-URL: Repository, https://github.com/akaszynski/lsdyna-mesh-reader
Requires-Python: >=3.9
Requires-Dist: numpy>=1.22.4
Provides-Extra: docs
Requires-Dist: pydata-sphinx-theme; extra == "docs"
Requires-Dist: numpydoc; extra == "docs"
Requires-Dist: sphinx; extra == "docs"
Requires-Dist: sphinx-copybutton; extra == "docs"
Requires-Dist: myst-parser; extra == "docs"
Provides-Extra: pyvista
Requires-Dist: pyvista; extra == "pyvista"
